briansfirstpackage/__init__.py
briansfirstpackage/add.py
briansfirstpackage/subtract.py
briansfirstpackage/extras/__init__.py
briansfirstpackage/extras/divide.py
briansfirstpackage/extras/multiply.py
briansfirstpackage-0.0.1.dist-info/METADATA
briansfirstpackage-0.0.1.dist-info/WHEEL
briansfirstpackage-0.0.1.dist-info/top_level.txt
briansfirstpackage-0.0.1.dist-info/RECORD
