Metadata-Version: 2.1
Name: briansfirstpackage
Version: 0.0.1
Summary: An introductory package
Home-page: UNKNOWN
Author: Brian Hassard
Author-email: <iamthebriguy@gmail.com>
License: UNKNOWN
Keywords: python,first package
Platform: UNKNOWN
Classifier: Development Status :: 3 - Alpha
Classifier: Intended Audience :: Education
Classifier: Programming Language :: Python :: 3
Classifier: Operating System :: MacOS :: MacOS X
Classifier: Operating System :: Microsoft :: Windows
